openstack/__init__.py
openstack/aksksession.py
openstack/connection.py
openstack/exceptions.py
openstack/format.py
openstack/module_loader.py
openstack/profile.py
openstack/proxy.py
openstack/proxy2.py
openstack/resource.py
openstack/resource2.py
openstack/service_endpoint.py
openstack/service_filter.py
openstack/session.py
openstack/tokenid_session.py
openstack/utils.py
openstack/version.py
openstack/anti_ddos/__init__.py
openstack/anti_ddos/anti_ddos_service.py
openstack/anti_ddos/version.py
openstack/anti_ddos/v1/__init__.py
openstack/anti_ddos/v1/_proxy.py
openstack/anti_ddos/v1/antiddos.py
openstack/anti_ddos/v1/warnalert.py
openstack/auto_scaling/__init__.py
openstack/auto_scaling/auto_scaling_service.py
openstack/auto_scaling/version.py
openstack/auto_scaling/v1/__init__.py
openstack/auto_scaling/v1/_proxy.py
openstack/auto_scaling/v1/activity.py
openstack/auto_scaling/v1/config.py
openstack/auto_scaling/v1/group.py
openstack/auto_scaling/v1/instance.py
openstack/auto_scaling/v1/lifecycle_hook.py
openstack/auto_scaling/v1/notification.py
openstack/auto_scaling/v1/policy.py
openstack/auto_scaling/v1/quota.py
openstack/auto_scaling/v1/tag.py
openstack/bare_metal/__init__.py
openstack/bare_metal/bare_metal_service.py
openstack/bare_metal/version.py
openstack/bare_metal/v1/__init__.py
openstack/bare_metal/v1/_proxy.py
openstack/bare_metal/v1/chassis.py
openstack/bare_metal/v1/driver.py
openstack/bare_metal/v1/node.py
openstack/bare_metal/v1/port.py
openstack/bare_metal/v1/port_group.py
openstack/block_store/__init__.py
openstack/block_store/block_store_service.py
openstack/block_store/v2/__init__.py
openstack/block_store/v2/_proxy.py
openstack/block_store/v2/availability_zone.py
openstack/block_store/v2/extension.py
openstack/block_store/v2/snapshot.py
openstack/block_store/v2/type.py
openstack/block_store/v2/volume.py
openstack/block_store/v2/volume_transfer.py
openstack/bms/__init__.py
openstack/bms/bms_service.py
openstack/bms/version.py
huaweicloud_sdk_python-1.0.28.dist-info/LICENSE
huaweicloud_sdk_python-1.0.28.dist-info/METADATA
huaweicloud_sdk_python-1.0.28.dist-info/Notice.md
huaweicloud_sdk_python-1.0.28.dist-info/WHEEL
huaweicloud_sdk_python-1.0.28.dist-info/top_level.txt
huaweicloud_sdk_python-1.0.28.dist-info/RECORD
