Metadata-Version: 2.1
Name: huaweicloud-sdk-python
Version: 1.0.28
Summary: An SDK for building applications to work with OpenStack
Home-page: https://github.com/huaweicloud/huaweicloud-sdk-python
Author: huawei
Author-email: UNKNOWN
License: UNKNOWN
Platform: UNKNOWN
Classifier: Environment :: OpenStack
Classifier: Intended Audience :: Information Technology
Classifier: Intended Audience :: System Administrators
Classifier: License :: OSI Approved :: Apache Software License
Classifier: Operating System :: POSIX :: Linux
Classifier: Programming Language :: Python
Classifier: Programming Language :: Python :: 2.7
Classifier: Programming Language :: Python :: 3.4
Classifier: Programming Language :: Python :: 3.5
Classifier: Programming Language :: Python :: 3.6
Classifier: Programming Language :: Python :: 3.7
Requires-Dist: pbr (!=2.1.0,>=2.0.0)
Requires-Dist: six (>=1.9.0)
Requires-Dist: stevedore (>=1.20.0)
Requires-Dist: keystoneauth1 (<=3.4.0,>=3.0.0)
Requires-Dist: deprecation (>=1.0)
